CHANGELOG.md
LICENSE
README.md
hyperfocus/__init__.py
hyperfocus/config/__init__.py
hyperfocus/config/config.py
hyperfocus/config/exceptions.py
hyperfocus/config/file.py
hyperfocus/config/policy.py
hyperfocus/console/__init__.py
hyperfocus/console/cli.py
hyperfocus/console/commands/__init__.py
hyperfocus/console/commands/_shortcodes.py
hyperfocus/console/commands/add.py
hyperfocus/console/commands/config.py
hyperfocus/console/commands/copy.py
hyperfocus/console/commands/delete.py
hyperfocus/console/commands/done.py
hyperfocus/console/commands/edit.py
hyperfocus/console/commands/init.py
hyperfocus/console/commands/log.py
hyperfocus/console/commands/main.py
hyperfocus/console/commands/reset.py
hyperfocus/console/commands/show.py
hyperfocus/console/commands/stash.py
hyperfocus/console/commands/status.py
hyperfocus/console/core/__init__.py
hyperfocus/console/core/arguments.py
hyperfocus/console/core/error_handler.py
hyperfocus/console/core/group.py
hyperfocus/console/core/hyperfocus.py
hyperfocus/console/core/options.py
hyperfocus/console/core/parameters.py
hyperfocus/console/exceptions.py
hyperfocus/database/__init__.py
hyperfocus/database/_database.py
hyperfocus/database/error_handler.py
hyperfocus/database/exceptions.py
hyperfocus/database/models.py
hyperfocus/exceptions.py
hyperfocus/locations.py
hyperfocus/services/__init__.py
hyperfocus/services/daily_tracker.py
hyperfocus/services/exceptions.py
hyperfocus/services/history.py
hyperfocus/services/session.py
hyperfocus/services/stash_box.py
hyperfocus/termui/__init__.py
hyperfocus/termui/components.py
hyperfocus/termui/exceptions.py
hyperfocus/termui/formatter.py
hyperfocus/termui/icons.py
hyperfocus/termui/markup.py
hyperfocus/termui/printer.py
hyperfocus/termui/prompt.py
hyperfocus/termui/style.py
hyperfocus/utils.py
hyperfocus-1.2.0.dist-info/entry_points.txt
hyperfocus-1.2.0.dist-info/LICENSE
hyperfocus-1.2.0.dist-info/METADATA
hyperfocus-1.2.0.dist-info/WHEEL
hyperfocus-1.2.0.dist-info/RECORD
