Metadata-Version: 2.1
Name: hyperfocus
Version: 1.2.0
Summary: Minimalist daily task manager.
Home-page: https://github.com/u8slvn/hyperfocus
License: MIT
Keywords: cli,todo,todolist,todo-list,task-list,productivity
Author: u8slvn
Author-email: u8slvn@gmail.com
Requires-Python: >=3.8,<4.0
Classifier: License :: OSI Approved :: MIT License
Classifier: Programming Language :: Python :: 3
Classifier: Programming Language :: Python :: 3.8
Classifier: Programming Language :: Python :: 3.9
Classifier: Programming Language :: Python :: 3.10
Classifier: Programming Language :: Python :: 3.11
Classifier: Programming Language :: Python :: 3.12
Requires-Dist: click (>=8.1.3,<9.0.0)
Requires-Dist: peewee (>=3.17.0,<4.0.0)
Requires-Dist: pyperclip (>=1.8.2,<2.0.0)
Project-URL: Changelog, https://github.com/u8slvn/hyperfocus/blob/main/CHANGELOG.md
Project-URL: Repository, https://github.com/u8slvn/hyperfocus
